kan_linear/__init__.py
kan_linear/kan.py
kan_linear-1.0.1.dist-info/licenses/LICENSE
kan_linear-1.0.1.dist-info/METADATA
kan_linear-1.0.1.dist-info/WHEEL
kan_linear-1.0.1.dist-info/top_level.txt
kan_linear-1.0.1.dist-info/RECORD
