Metadata-Version: 2.4
Name: kan_linear
Version: 1.0.1
Summary: A KANLinear layer implementation using PyTorch
Author-email: Cross <cross@dill.moe>
Project-URL: Homepage, https://github.com/dillfrescott/kan_linear
Classifier: Programming Language :: Python :: 3
Classifier: License :: OSI Approved :: MIT License
Classifier: Operating System :: OS Independent
Requires-Python: >=3.7
License-File: LICENSE
Requires-Dist: torch
Dynamic: license-file
